shippinglabel_conda/__init__.py
shippinglabel_conda/__main__.py
shippinglabel_conda/py.typed
shippinglabel_conda-0.1.0.post1.dist-info/LICENSE
shippinglabel_conda-0.1.0.post1.dist-info/METADATA
shippinglabel_conda-0.1.0.post1.dist-info/WHEEL
shippinglabel_conda-0.1.0.post1.dist-info/entry_points.txt
shippinglabel_conda-0.1.0.post1.dist-info/RECORD
