Metadata-Version: 2.1
Name: shippinglabel-conda
Version: 0.1.0.post1
Summary: Shippinglabel extension with utilities conda packages.
Author-email: Dominic Davis-Foster <dominic@davis-foster.co.uk>
License: MIT
Keywords: conda,packaging,pypi,requirements,shippinglabel
Home-page: https://github.com/domdfcoding/shippinglabel-conda
Project-URL: Issue Tracker, https://github.com/domdfcoding/shippinglabel-conda/issues
Project-URL: Source Code, https://github.com/domdfcoding/shippinglabel-conda
Platform: Windows
Platform: macOS
Platform: Linux
Classifier: Development Status :: 5 - Production/Stable
Classifier: Intended Audience :: Developers
Classifier: License :: OSI Approved :: MIT License
Classifier: Operating System :: OS Independent
Classifier: Programming Language :: Python
Classifier: Programming Language :: Python :: 3 :: Only
Classifier: Programming Language :: Python :: 3.6
Classifier: Programming Language :: Python :: 3.7
Classifier: Programming Language :: Python :: 3.8
Classifier: Programming Language :: Python :: 3.9
Classifier: Programming Language :: Python :: 3.10
Classifier: Programming Language :: Python :: 3.11
Classifier: Programming Language :: Python :: 3.12
Classifier: Programming Language :: Python :: Implementation :: CPython
Classifier: Programming Language :: Python :: Implementation :: PyPy
Classifier: Topic :: Software Development :: Libraries :: Python Modules
Classifier: Topic :: System :: Archiving :: Packaging
Classifier: Typing :: Typed
Requires-Python: >=3.6
Requires-Dist: apeye>=1.0.0
Requires-Dist: domdf-python-tools>=3.3.0
Requires-Dist: packaging>=20.9
Requires-Dist: platformdirs>=2.3.0
Requires-Dist: shippinglabel>=1.3.0
